requests_pelican/__init__.py
requests_pelican/_version.py
requests_pelican/adapters.py
requests_pelican/auth.py
requests_pelican/config.py
requests_pelican/director.py
requests_pelican/federation.py
requests_pelican/pelican.py
requests_pelican/py.typed
requests_pelican/requests.py
requests_pelican/sessions.py
requests_pelican/utils.py
requests_pelican/tests/__init__.py
requests_pelican/tests/conftest.py
requests_pelican/tests/test_adapters.py
requests_pelican/tests/test_config.py
requests_pelican/tests/test_director.py
requests_pelican/tests/test_integration.py
requests_pelican/tests/test_utils.py
requests_pelican-0.2.0.dist-info/LICENSE
requests_pelican-0.2.0.dist-info/METADATA
requests_pelican-0.2.0.dist-info/WHEEL
requests_pelican-0.2.0.dist-info/top_level.txt
requests_pelican-0.2.0.dist-info/RECORD
