Metadata-Version: 2.2
Name: requests-pelican
Version: 0.2.0
Summary: A requests addon for Pelican data federations
Author-email: Duncan Macleod <duncan.macleod@ligo.org>
License: MIT
Project-URL: Homepage, https://git.ligo.org/computing/software/requests-pelican
Project-URL: Bug Tracker, https://git.ligo.org/computing/software/requests-pelican/-/issues
Project-URL: Documentation, https://requests-pelican.readthedocs.io/en/stable
Project-URL: Source Code, https://git.ligo.org/computing/software/requests-pelican
Classifier: Development Status :: 2 - Pre-Alpha
Classifier: Intended Audience :: Science/Research
Classifier: License :: OSI Approved :: MIT License
Classifier: Natural Language :: English
Classifier: Operating System :: OS Independent
Classifier: Programming Language :: Python
Classifier: Programming Language :: Python :: 3
Classifier: Programming Language :: Python :: 3.9
Classifier: Programming Language :: Python :: 3.10
Classifier: Programming Language :: Python :: 3.11
Classifier: Programming Language :: Python :: 3.12
Classifier: Programming Language :: Python :: 3.13
Classifier: Topic :: Scientific/Engineering :: Astronomy
Classifier: Topic :: Scientific/Engineering :: Physics
Requires-Python: >=3.9
License-File: LICENSE
Requires-Dist: requests>=2.32.3
Provides-Extra: docs
Requires-Dist: furo; extra == "docs"
Requires-Dist: Sphinx; extra == "docs"
Requires-Dist: sphinx-automodapi; extra == "docs"
Provides-Extra: scitokens
Requires-Dist: requests-scitokens>=0.1.0; extra == "scitokens"
Provides-Extra: test
Requires-Dist: pytest>=3.9.1; extra == "test"
Requires-Dist: pytest-cov; extra == "test"
Requires-Dist: pytest-remotedata; extra == "test"
Requires-Dist: requests-mock; extra == "test"
